Metadata-Version: 2.1
Name: Pixelworlds
Version: 0.1.4
Summary: 🌎 A python wrapper for pixel worlds' data
Home-page: https://github.com/zenqii/pixelworldsapi
Author: Zenqi
License: MIT
Download-URL: https://github.com/zenqii/pixelworldsapi/tarball/main
Keywords: api,pixelworlds
Platform: Windows
Classifier: Development Status :: 4 - Beta
Classifier: Intended Audience :: Developers
Classifier: Intended Audience :: Education
Classifier: License :: OSI Approved :: MIT License
Classifier: Natural Language :: English
Classifier: Operating System :: Microsoft :: Windows
Classifier: Programming Language :: Python :: 3.5
Classifier: Programming Language :: Python :: 3.6
Classifier: Programming Language :: Python :: 3.7
Classifier: Programming Language :: Python :: 3.8
Classifier: Topic :: Software Development
Classifier: Topic :: Software Development :: Libraries :: Python Modules
Requires-Python: >=3.5
